qt_command_palette/__about__.py
qt_command_palette/__init__.py
qt_command_palette/_api.py
qt_command_palette/_commands.py
qt_command_palette/_list.py
qt_command_palette/_storage.py
qt_command_palette/_widget.py
qt_command_palette-0.0.10.dist-info/METADATA
qt_command_palette-0.0.10.dist-info/WHEEL
qt_command_palette-0.0.10.dist-info/licenses/LICENSE.txt
qt_command_palette-0.0.10.dist-info/RECORD
