Metadata-Version: 2.3
Name: qt-command-palette
Version: 0.0.10
Summary: A command palette widget for Qt applications
Project-URL: Documentation, https://github.com/unknown/qt-command-palette#readme
Project-URL: Issues, https://github.com/unknown/qt-command-palette/issues
Project-URL: Source, https://github.com/unknown/qt-command-palette
Author-email: Hanjin Liu <hanjin.liu@bs.s.u-tokyo.ac.jp>
License: MIT License
License-File: LICENSE.txt
Classifier: Development Status :: 4 - Beta
Classifier: Programming Language :: Python
Classifier: Programming Language :: Python :: 3.8
Classifier: Programming Language :: Python :: 3.9
Classifier: Programming Language :: Python :: 3.10
Classifier: Programming Language :: Python :: 3.11
Classifier: Programming Language :: Python :: 3.12
Classifier: Programming Language :: Python :: Implementation :: CPython
Classifier: Programming Language :: Python :: Implementation :: PyPy
Requires-Python: >=3.8
Requires-Dist: qtpy>=2.0.0
